blog_agent_framework/__init__.py
blog_agent_framework/config.py
blog_agent_framework/agents/__init__.py
blog_agent_framework/agents/critic.py
blog_agent_framework/agents/reviewers.py
blog_agent_framework/agents/writer.py
blog_agent_framework/utils/__init__.py
blog_agent_framework/utils/helpers.py
blog_agent_framework-1.0.1.dist-info/licenses/LICENSE
blog_agent_framework-1.0.1.dist-info/METADATA
blog_agent_framework-1.0.1.dist-info/WHEEL
blog_agent_framework-1.0.1.dist-info/top_level.txt
blog_agent_framework-1.0.1.dist-info/RECORD
