Metadata-Version: 2.4
Name: blog-agent-framework
Version: 1.0.1
Summary: An AI-powered library that orchestrates a team of agents to generate SEO-optimized, easy-to-read, story-based blog posts
Author-email: Edilma Riano <edilmadev@gmail.com>
License: MIT License
Project-URL: Homepage, https://github.com/edilma/AI-Agent-Orchestrator
Project-URL: Documentation, https://github.com/edilma/AI-Agent-Orchestrator#readme
Project-URL: Bug Tracker, https://github.com/edilma/AI-Agent-Orchestrator/issues
Project-URL: Source, https://github.com/edilma/AI-Agent-Orchestrator
Keywords: ai,autogen,llm,agent,orchestrator,content-generation,seo,blog,marketing,automation
Classifier: Development Status :: 5 - Production/Stable
Classifier: Intended Audience :: Developers
Classifier: Intended Audience :: Information Technology
Classifier: License :: OSI Approved :: MIT License
Classifier: Programming Language :: Python :: 3
Classifier: Programming Language :: Python :: 3.11
Classifier: Programming Language :: Python :: 3.12
Classifier: Operating System :: OS Independent
Classifier: Topic :: Scientific/Engineering :: Artificial Intelligence
Classifier: Topic :: Software Development :: Libraries
Classifier: Topic :: Text Processing :: General
Classifier: Topic :: Internet :: WWW/HTTP :: Dynamic Content
Classifier: Topic :: Utilities
Classifier: Topic :: Text Processing :: General
Requires-Python: >=3.11
License-File: LICENSE
Requires-Dist: autogen-agentchat>=0.2.17
Requires-Dist: autogen-ext[openai]>=0.6.4
Requires-Dist: openai
Provides-Extra: dev
Requires-Dist: python-dotenv>=1.0.0; extra == "dev"
Dynamic: license-file
